{
  "project_info": {
    "project_number": "694724494382",
    "firebase_url": "https://sqllite-c2650.firebaseio.com",
    "project_id": "sqllite-c2650",
    "storage_bucket": "sqllite-c2650.appspot.com"
  },
  "client": [
    {
      "client_info": {
        "mobilesdk_app_id": "1:694724494382:android:bb4de7b6e4aee053",
        "android_client_info": {
          "package_name": "com.wather.andrzej.sqllite"
        }
      },
      "oauth_client": [
        {
          "client_id": "694724494382-0edjsljpci7iro39dici1f0jg5t8lvim.apps.googleusercontent.com",
          "client_type": 3
        }
      ],
      "api_key": [
        {
          "current_key": "AIzaSyAcaYI9ljLVvZLTwftwcjCwxSGGNsqLvf4"
        }
      ],
      "services": {
        "analytics_service": {
          "status": 1
        },
        "appinvite_service": {
          "status": 1,
          "other_platform_oauth_client": []
        },
        "ads_service": {
          "status": 2
        }
      }
    }
  ],
  "configuration_version": "1"
}